{
  "products": [
       {
          "id": "airpods-pro",
          "name": "Apple Airpods Pro",
          "details": "Met Apple AirPods Pro worden jouw favoriete deuntjes niet meer onderbroken door een luidruchtige omgeving.",
          "price": "€139.99",
          "oldprice": "€199.99",
          "image": "https://i.ibb.co/qr7qDPW/img-airpods-removebg-preview.png",
          "vendor": "Coolblue",
          "vendorlink": "https://www.coolblue.nl/product/852042/apple-airpods-pro-met-draadloze-oplaadcase.html"
        },
      {
          "id": "ipad-air",
          "name": "Apple iPad Air",
          "details": "Apple iPad Air (3e generatie, 2019) 64GB Wifi + 4G Space Gray gebruik je als vervanger voor je laptop dankzij de krachtige A12 bionic-chip.",
          "price": "€349.99",
          "oldprice": "€449.99",
          "image": "https://i.ibb.co/Pwr5KrX/1415008-removebg-preview.png",
          "vendor": "Amazon",
          "vendorlink": "https://www.amazon.de/dp/B07PSKYKGK/ref=cm_sw_em_r_mt_dp_U_e4cgFbR2KNWW5"
        },
      {
          "id": "canon-eos-6d",
          "name": "Canon EOS 6D",
          "details": "De Canon EOS 6D Mark II Body is een spiegelreflexcamera met een 26,2 megapixel full frame sensor en DIGIC 7 beeldprocessor.",
          "price": "€1319.95",
          "oldprice": "€1559.95",
          "image": "https://i.ibb.co/r2D02yM/1382363-removebg-preview.png",
          "vendor": "Coolblue",
          "vendorlink": "https://www.coolblue.nl/product/784843/canon-eos-6d-mark-ii-body.html"
        },
      {
          "id": "garmin-vivoactive-4l",
          "name": "Garmin Vivoactive 4L",
          "details": "Waak over je gezondheid met verbeter deze met de Garmin Vivoactive 4. Naast standaard gegevens meet het ook je fitnessleeftijd aan de hand van een VO2 max meting. ",
          "price": "€329",
          "oldprice": "€269",
          "image": "https://i.ibb.co/mvcjktW/1388447-removebg-preview.png",
          "vendor": "Coolblue",
          "vendorlink": "https://www.coolblue.nl/product/836165/garmin-vivoactive-4l-zwart-45-mm.html"
        }
  ],
  "profile": {
    "name": "viktorrenkema"
  }
}
